pyiterable/__init__.py
pyiterable/iterable.py
pyiterable-0.4.0.dist-info/DESCRIPTION.rst
pyiterable-0.4.0.dist-info/METADATA
pyiterable-0.4.0.dist-info/RECORD
pyiterable-0.4.0.dist-info/WHEEL
pyiterable-0.4.0.dist-info/metadata.json
pyiterable-0.4.0.dist-info/top_level.txt
