Metadata-Version: 2.0
Name: pyiterable
Version: 0.4.0
Summary: Iterable chains
Home-page: https://github.com/neverendingqs/pyiterable
Author: neverendingqs
Author-email: mark.tse@neverendingqs.com
License: MIT
Platform: UNKNOWN
Classifier: Development Status :: 4 - Beta
Classifier: License :: OSI Approved :: Apache Software License
Classifier: Programming Language :: Python :: 2.7
Classifier: Programming Language :: Python :: 3.4
Classifier: Programming Language :: Python :: 3.5
Classifier: Topic :: Software Development :: Libraries :: Python Modules
